odoo/addons/sale_stock_prebook_cancel_line/README.rst
odoo/addons/sale_stock_prebook_cancel_line/__init__.py
odoo/addons/sale_stock_prebook_cancel_line/__manifest__.py
odoo/addons/sale_stock_prebook_cancel_line/i18n/it.po
odoo/addons/sale_stock_prebook_cancel_line/i18n/sale_stock_prebook_cancel_line.pot
odoo/addons/sale_stock_prebook_cancel_line/models/__init__.py
odoo/addons/sale_stock_prebook_cancel_line/models/sale_order_line.py
odoo/addons/sale_stock_prebook_cancel_line/models/stock_move.py
odoo/addons/sale_stock_prebook_cancel_line/readme/CONTRIBUTORS.md
odoo/addons/sale_stock_prebook_cancel_line/readme/CREDITS.md
odoo/addons/sale_stock_prebook_cancel_line/readme/DESCRIPTION.md
odoo/addons/sale_stock_prebook_cancel_line/static/description/icon.png
odoo/addons/sale_stock_prebook_cancel_line/static/description/index.html
odoo/addons/sale_stock_prebook_cancel_line/tests/__init__.py
odoo/addons/sale_stock_prebook_cancel_line/tests/test_sale_stock_prebook_cancel_line.py
odoo_addon_sale_stock_prebook_cancel_line-16.0.1.0.0.5.dist-info/METADATA
odoo_addon_sale_stock_prebook_cancel_line-16.0.1.0.0.5.dist-info/WHEEL
odoo_addon_sale_stock_prebook_cancel_line-16.0.1.0.0.5.dist-info/top_level.txt
odoo_addon_sale_stock_prebook_cancel_line-16.0.1.0.0.5.dist-info/RECORD
