Metadata-Version: 2.1
Name: odoo-addon-sale_stock_prebook_cancel_line
Version: 16.0.1.0.0.5
Summary: Takes into account prebook pickings into the computation of cancelled qty on the sale order lines
Home-page: https://github.com/OCA/sale-prebook
Author: ACSONE SA/NV,Odoo Community Association (OCA)
Author-email: support@odoo-community.org
License: AGPL-3
Classifier: Programming Language :: Python
Classifier: Framework :: Odoo
Classifier: Framework :: Odoo :: 16.0
Classifier: License :: OSI Approved :: GNU Affero General Public License v3
Requires-Python: >=3.10
Requires-Dist: odoo-addon-sale-order-line-cancel<16.1dev,>=16.0dev
Requires-Dist: odoo-addon-sale-stock-prebook<16.1dev,>=16.0dev
Requires-Dist: odoo<16.1dev,>=16.0a
